neuralpp/__init__.py
neuralpp/experiments/__init__.py
neuralpp/experiments/mnist_supervised.py
neuralpp/experiments/negative_learning.py
neuralpp/experiments/mnist_semi_supervised/__init__.py
neuralpp/experiments/mnist_semi_supervised/mnist_semi_supervised.py
neuralpp/experiments/mnist_semi_supervised/successive_digits.py
neuralpp/experiments/mnist_semi_supervised/sum_of_pair.py
neuralpp/inference/__init__.py
neuralpp/inference/graphical_model/__init__.py
neuralpp/inference/graphical_model/brute_force.py
neuralpp/inference/graphical_model/variable_elimination.py
neuralpp/inference/graphical_model/learn/__init__.py
neuralpp/inference/graphical_model/learn/graphical_model_sgd_learner.py
neuralpp/inference/graphical_model/learn/learning_problem_solver.py
neuralpp/inference/graphical_model/learn/uniform_training.py
neuralpp/inference/graphical_model/representation/__init__.py
neuralpp/inference/graphical_model/representation/representation.py
neuralpp/inference/graphical_model/representation/factor/__init__.py
neuralpp/inference/graphical_model/representation/factor/atomic_factor.py
neuralpp/inference/graphical_model/representation/factor/factor.py
neuralpp/inference/graphical_model/representation/factor/product_factor.py
neuralpp/inference/graphical_model/representation/factor/pytorch_table_factor.py
neuralpp/inference/graphical_model/representation/factor/table_factor.py
neuralpp/inference/graphical_model/representation/factor/continuous/__init__.py
neuralpp/inference/graphical_model/representation/factor/continuous/continuous_factor.py
neuralpp/inference/graphical_model/representation/factor/continuous/continuous_internal_parameterless_factor.py
neuralpp/inference/graphical_model/representation/factor/continuous/normal_factor.py
neuralpp/inference/graphical_model/representation/factor/continuous/pytorch_distribution_factor.py
neuralpp/inference/graphical_model/representation/factor/fixed/__init__.py
neuralpp-0.1.1.dist-info/LICENSE.txt
neuralpp-0.1.1.dist-info/METADATA
neuralpp-0.1.1.dist-info/WHEEL
neuralpp-0.1.1.dist-info/top_level.txt
neuralpp-0.1.1.dist-info/RECORD
