Metadata-Version: 2.1
Name: neuralpp
Version: 0.1.1
Summary: Neural Probabilistic Programs (NeuralPPs)
Home-page: https://github.com/rodrigodesalvobraz/neuralpp
Author: Rodrigo de Salvo Braz
License: MIT
Project-URL: Documentation, https://github.com/rodrigodesalvobraz/neuralpp
Project-URL: Source, https://github.com/rodrigodesalvobraz/neuralpp
Keywords: Bayesian Inference,Exact Inference,PyTorch
Platform: UNKNOWN
Classifier: Development Status :: 3 - Alpha
Classifier: Programming Language :: Python :: 3 :: Only
Classifier: License :: OSI Approved :: MIT License
Classifier: Topic :: Scientific/Engineering
Classifier: Intended Audience :: Science/Research
Classifier: Intended Audience :: Developers
Requires-Python: >=3.8
Requires-Dist: torch (>=1.8.1)
Provides-Extra: dev
Requires-Dist: cudatoolkit ; extra == 'dev'
Requires-Dist: pytorch ; extra == 'dev'
Requires-Dist: torchaudio ; extra == 'dev'
Requires-Dist: torchvision ; extra == 'dev'
Requires-Dist: matplotlib ; extra == 'dev'
Requires-Dist: tqdm ; extra == 'dev'
Requires-Dist: pytest ; extra == 'dev'
Requires-Dist: pytest-cov ; extra == 'dev'
Requires-Dist: black ; extra == 'dev'
Requires-Dist: flake8 ; extra == 'dev'
Requires-Dist: flake8-bugbear ; extra == 'dev'
Requires-Dist: mypy ; extra == 'dev'
Requires-Dist: usort ; extra == 'dev'
Provides-Extra: test
Requires-Dist: cudatoolkit ; extra == 'test'
Requires-Dist: pytorch ; extra == 'test'
Requires-Dist: torchaudio ; extra == 'test'
Requires-Dist: torchvision ; extra == 'test'
Requires-Dist: matplotlib ; extra == 'test'
Requires-Dist: tqdm ; extra == 'test'
Requires-Dist: pytest ; extra == 'test'
Requires-Dist: pytest-cov ; extra == 'test'
